masutils/__init__.py
masutils/dl.py
masutils/ml2.py
masutils/ml3.py
masutils/nlp.py
masutils/perceptron.py
masutils/tsf.py
masutils-0.0.6.dist-info/LICENSE
masutils-0.0.6.dist-info/METADATA
masutils-0.0.6.dist-info/WHEEL
masutils-0.0.6.dist-info/top_level.txt
masutils-0.0.6.dist-info/RECORD
