Metadata-Version: 2.1
Name: masutils
Version: 0.0.6
Summary: A small package for perceptron
Home-page: https://github.com/Samm-G/masutils
Author: Samm-G
Author-email: gsamarth97@gmail.com
Project-URL: Bug Tracker, https://github.com/Samm-G/masutils/issues
Classifier: Programming Language :: Python :: 3
Classifier: License :: OSI Approved :: MIT License
Classifier: Operating System :: OS Independent
Requires-Python: >=3.6
License-File: LICENSE
